[
  {
    "word": "the",
    "value": 31,
    "category": "Determiner",
    "translation": "el"
  },
  {
    "word": "cinderella",
    "value": 25,
    "category": "Noun",
    "translation": "Cenicienta"
  },
  {
    "word": "said",
    "value": 20,
    "category": "Verb",
    "translation": "dicho"
  },
  {
    "word": "tree",
    "value": 18,
    "category": "Noun",
    "translation": "\u00e1rbol"
  },
  {
    "word": "prince",
    "value": 18,
    "category": "Noun",
    "translation": "Pr\u00edncipe"
  },
  {
    "word": "when",
    "value": 16,
    "category": "Wh-Adverb",
    "translation": "cuando"
  },
  {
    "word": "came",
    "value": 16,
    "category": "Verb",
    "translation": "vino"
  },
  {
    "word": "go",
    "value": 16,
    "category": "Verb",
    "translation": "ir"
  },
  {
    "word": "shoe",
    "value": 16,
    "category": "Noun",
    "translation": "zapato"
  },
  {
    "word": "went",
    "value": 15,
    "category": "Verb",
    "translation": "fue"
  },
  {
    "word": "two",
    "value": 15,
    "category": "Numeral",
    "translation": "dos"
  },
  {
    "word": "she",
    "value": 14,
    "category": "Pronoun",
    "translation": "ella"
  },
  {
    "word": "took",
    "value": 13,
    "category": "Verb",
    "translation": "tom\u00f3"
  },
  {
    "word": "pick",
    "value": 13,
    "category": "Noun",
    "translation": "elegir"
  },
  {
    "word": "beautiful",
    "value": 12,
    "category": "Adjective",
    "translation": "hermoso"
  },
  {
    "word": "girl",
    "value": 11,
    "category": "Noun",
    "translation": "chica"
  },
  {
    "word": "one",
    "value": 11,
    "category": "Numeral",
    "translation": "uno"
  },
  {
    "word": "pigeons",
    "value": 11,
    "category": "Noun",
    "translation": "palomas"
  },
  {
    "word": "ashes",
    "value": 10,
    "category": "Noun",
    "translation": "cenizas"
  },
  {
    "word": "bride",
    "value": 10,
    "category": "Noun",
    "translation": "novia"
  },
  {
    "word": "he",
    "value": 10,
    "category": "Pronoun",
    "translation": "\u00e9l"
  },
  {
    "word": "away",
    "value": 9,
    "category": "Adverb",
    "translation": "lejos"
  },
  {
    "word": "home",
    "value": 9,
    "category": "Noun",
    "translation": "hogar"
  },
  {
    "word": "hazel",
    "value": 9,
    "category": "Noun",
    "translation": "color avellana"
  },
  {
    "word": "would",
    "value": 9,
    "category": "Modal",
    "translation": "har\u00eda"
  },
  {
    "word": "festival",
    "value": 9,
    "category": "Noun",
    "translation": "festival"
  },
  {
    "word": "stepmother",
    "value": 9,
    "category": "Noun",
    "translation": "madrastra"
  },
  {
    "word": "mother",
    "value": 8,
    "category": "Noun",
    "translation": "madre"
  },
  {
    "word": "they",
    "value": 8,
    "category": "Pronoun",
    "translation": "ellos"
  },
  {
    "word": "then",
    "value": 8,
    "category": "Adverb",
    "translation": "entonces"
  },
  {
    "word": "foot",
    "value": 8,
    "category": "Noun",
    "translation": "pie"
  },
  {
    "word": "good",
    "value": 7,
    "category": "Adjective",
    "translation": "bien"
  },
  {
    "word": "grave",
    "value": 7,
    "category": "Noun",
    "translation": "tumba"
  },
  {
    "word": "pick",
    "value": 7,
    "category": "Verb",
    "translation": "elegir"
  },
  {
    "word": "bird",
    "value": 7,
    "category": "Noun",
    "translation": "p\u00e1jaro"
  },
  {
    "word": "you",
    "value": 7,
    "category": "Pronoun",
    "translation": "t\u00fa"
  },
  {
    "word": "dance",
    "value": 7,
    "category": "Verb",
    "translation": "bailar"
  },
  {
    "word": "dress",
    "value": 7,
    "category": "Noun",
    "translation": "vestido"
  },
  {
    "word": "right",
    "value": 7,
    "category": "Adjective",
    "translation": "bien"
  },
  {
    "word": "day",
    "value": 6,
    "category": "Noun",
    "translation": "d\u00eda"
  },
  {
    "word": "white",
    "value": 6,
    "category": "Adjective",
    "translation": "blanco"
  },
  {
    "word": "this",
    "value": 6,
    "category": "Determiner",
    "translation": "este"
  },
  {
    "word": "kitchen",
    "value": 6,
    "category": "Noun",
    "translation": "cocina"
  },
  {
    "word": "clothes",
    "value": 6,
    "category": "Noun",
    "translation": "ropa"
  },
  {
    "word": "gave",
    "value": 6,
    "category": "Verb",
    "translation": "dio"
  },
  {
    "word": "one",
    "value": 6,
    "category": "Noun",
    "translation": "uno"
  },
  {
    "word": "began",
    "value": 6,
    "category": "Verb",
    "translation": "comenz\u00f3"
  },
  {
    "word": "gold",
    "value": 6,
    "category": "Noun",
    "translation": "oro"
  },
  {
    "word": "rook",
    "value": 6,
    "category": "Verb",
    "translation": "torre"
  },
  {
    "word": "di",
    "value": 6,
    "category": "Adjective",
    "translation": "di"
  }
]
